content_negotiation/__init__.py
content_negotiation/content_negotiation.py
content_negotiation/language_negotiation.py
content_negotiation-1.1.2.dist-info/LICENSE
content_negotiation-1.1.2.dist-info/WHEEL
content_negotiation-1.1.2.dist-info/METADATA
content_negotiation-1.1.2.dist-info/RECORD
