Metadata-Version: 2.1
Name: content-negotiation
Version: 1.1.2
Summary: A library for deciding content-type based on media ranges in HTTP Accept headers.
Home-page: https://github.com/Informasjonsforvaltning/content-negotiation
License: Apache-2.0
Author: Stig B. Dørmænen
Author-email: stigbd@gmail.com
Requires-Python: >=3.8,<4.0
Classifier: License :: OSI Approved :: Apache Software License
Classifier: Operating System :: OS Independent
Classifier: Programming Language :: Python :: 3
Classifier: Programming Language :: Python :: 3.8
Classifier: Programming Language :: Python :: 3.9
Classifier: Programming Language :: Python :: 3.10
Classifier: Programming Language :: Python :: 3
Project-URL: Documentation, https://content-negotiation.readthedocs.io
Project-URL: Repository, https://github.com/Informasjonsforvaltning/content-negotiation
